TB4hooky/__init__.py
TB4hooky/Exception/GlobalExceptionHook.py
TB4hooky/Exception/SubclassError.py
TB4hooky/Exception/__init__.py
TB4hooky/Utils/ImportUtil.py
TB4hooky/Utils/LinkDealer.py
TB4hooky/Utils/__init__.py
TB4hooky/hooky/CacheObject.py
TB4hooky/hooky/Hooker.py
TB4hooky/hooky/Serializer.py
TB4hooky/hooky/__init__.py
TB4hooky/netLoader/AdapterConnectionRemote.py
TB4hooky/netLoader/ComplexImport.py
TB4hooky/netLoader/DaynamicImport.py
TB4hooky/netLoader/MetaFinder.py
TB4hooky/netLoader/ModuleLoader.py
TB4hooky/netLoader/PackageLoader.py
TB4hooky/netLoader/RemoteControl.py
TB4hooky/netLoader/SourceCodeManager.py
TB4hooky/netLoader/__init__.py
TB4hooky/typeInspect/Inspect.py
TB4hooky/typeInspect/__init__.py
TB4hooky-0.1.11.dist-info/LICENSE
TB4hooky-0.1.11.dist-info/METADATA
TB4hooky-0.1.11.dist-info/WHEEL
TB4hooky-0.1.11.dist-info/top_level.txt
TB4hooky-0.1.11.dist-info/RECORD
