Metadata-Version: 2.1
Name: TB4hooky
Version: 0.1.11
Summary: Python hook framework support Local hook and Remote hook
Home-page: https://github.com/fateofdate/TB4hooky
Author: Fake77
Author-email: yankail520@gmail.com
Classifier: Programming Language :: Python :: 3
Classifier: License :: OSI Approved :: MIT License
Classifier: Operating System :: OS Independent
Requires-Python: >=3.7
License-File: LICENSE
Requires-Dist: aiohttp ==3.8.6
Requires-Dist: aiosignal ==1.3.1
Requires-Dist: async-timeout ==4.0.3
Requires-Dist: asynctest ==0.13.0
Requires-Dist: attrs ==23.2.0
Requires-Dist: bleach ==6.0.0
Requires-Dist: charset-normalizer ==3.3.2
Requires-Dist: click ==8.1.7
Requires-Dist: colorama ==0.4.6
Requires-Dist: docutils ==0.20.1
Requires-Dist: frozenlist ==1.3.3
Requires-Dist: fsspec ==2023.1.0
Requires-Dist: idna ==3.6
Requires-Dist: importlib-metadata ==6.7.0
Requires-Dist: importlib-resources ==5.12.0
Requires-Dist: itsdangerous ==2.1.2
Requires-Dist: jaraco.classes ==3.2.3
Requires-Dist: Jinja2 ==3.1.3
Requires-Dist: keyring ==24.1.1
Requires-Dist: loguru ==0.7.2
Requires-Dist: markdown-it-py ==2.2.0
Requires-Dist: MarkupSafe ==2.1.5
Requires-Dist: mdurl ==0.1.2
Requires-Dist: more-itertools ==9.1.0
Requires-Dist: multidict ==6.0.5
Requires-Dist: pkginfo ==1.10.0
Requires-Dist: Pygments ==2.17.2
Requires-Dist: pywin32-ctypes ==0.2.2
Requires-Dist: readme-renderer ==37.3
Requires-Dist: requests ==2.31.0
Requires-Dist: requests-toolbelt ==1.0.0
Requires-Dist: rfc3986 ==2.0.0
Requires-Dist: rich ==13.7.1
Requires-Dist: six ==1.16.0
Requires-Dist: tqdm ==4.66.2
Requires-Dist: twine ==4.0.2
Requires-Dist: typing-extensions ==4.7.1
Requires-Dist: urllib3 ==2.0.7
Requires-Dist: webencodings ==0.5.1
Requires-Dist: Werkzeug ==2.2.3
Requires-Dist: win32-setctime ==1.1.0
Requires-Dist: wincertstore ==0.2
Requires-Dist: yarl ==1.9.4
Requires-Dist: zipp ==3.15.0
Requires-Dist: certifi
